CGI/Carp.py
CGI/Cookie.py
CGI/Util.py
CGI/__init__.py
Class/Struct.py
Class/__init__.py
Config/__init__.py
Encode/Encoding.py
Encode/__init__.py
Encode/MIME/Name.py
Encode/MIME/__init__.py
Env/__init__.py
Exporter/__init__.py
File/Path.py
File/__init__.py
FindBin/__init__.py
HTML/Entities.py
HTML/__init__.py
Math/Complex.py
Math/__init__.py
Sys/Hostname.py
Sys/__init__.py
Text/ParseWords.py
Text/__init__.py
Time/HiRes.py
Time/__init__.py
Time/localtime.py
Time/tm.py
charnames/__init__.py
perllib/__init__.py
perllib-1.30.dist-info/AUTHORS.rst
perllib-1.30.dist-info/LICENSE
perllib-1.30.dist-info/METADATA
perllib-1.30.dist-info/WHEEL
perllib-1.30.dist-info/license.html
perllib-1.30.dist-info/top_level.txt
perllib-1.30.dist-info/RECORD
