Metadata-Version: 2.1
Name: perllib
Version: 1.30
Summary: Library functions to support pythonizer
Home-page: https://github.com/snoopyjc/pythonizer
Author: Joe Cool
Author-email: snoopyjc@gmail.com
License: Artistic License 2.0 - The Perl Foundation
Keywords: perllib
Classifier: Development Status :: 5 - Production/Stable
Classifier: Intended Audience :: Developers
Classifier: License :: OSI Approved :: Artistic License
Classifier: Natural Language :: English
Classifier: Programming Language :: Python :: 3
Classifier: Programming Language :: Python :: 3.8
Classifier: Programming Language :: Python :: 3.9
Classifier: Programming Language :: Python :: 3.10
Classifier: Programming Language :: Python :: 3.11
Requires-Python: >=3.8
License-File: LICENSE
License-File: license.html
License-File: AUTHORS.rst
